RpiL/CPU.py
RpiL/IR.py
RpiL/LED.py
RpiL/Motor_Driver.py
RpiL/PIR.py
RpiL/PWM.py
RpiL/RGB_LED.py
RpiL/Temperature_Sensor.py
RpiL/USDS.py
RpiL/__init__.py
RpiL/buzzer.py
RpiL/motor.py
RpiL/pin.py
rpi_gpio/Heat_Sensor.py
rpi_gpio/IR.py
rpi_gpio/LED.py
rpi_gpio/Motor_Driver.py
rpi_gpio/PIR.py
rpi_gpio/PWM.py
rpi_gpio/RGB_LED.py
rpi_gpio/Temperature_Sensor.py
rpi_gpio/USDS.py
rpi_gpio/__init__.py
rpi_gpio/buzzer.py
rpi_gpio/motor.py
rpi_gpio/pin.py
rpi_others/CPU.py
rpi_others/__init__.py
RpiL-0.2.3.1.dist-info/LICENSE
RpiL-0.2.3.1.dist-info/METADATA
RpiL-0.2.3.1.dist-info/WHEEL
RpiL-0.2.3.1.dist-info/top_level.txt
RpiL-0.2.3.1.dist-info/RECORD
